LICENSE
MANIFEST.in
README.md
requirements.txt
setup.cfg
setup.py
notebook_snapshot/__init__.py
notebook_snapshot/__meta__.py
notebook_snapshot/embed_html.py
notebook_snapshot/execute.py
notebook_snapshot/move.py
notebook_snapshot/params.py
notebook_snapshot/snapshot.py
notebook_snapshot/template.py
notebook_snapshot.egg-info/PKG-INFO
notebook_snapshot.egg-info/SOURCES.txt
notebook_snapshot.egg-info/dependency_links.txt
notebook_snapshot.egg-info/requires.txt
notebook_snapshot.egg-info/top_level.txt
notebook_snapshot/templates/hide_prompt.css
notebook_snapshot/templates/main.tpl.html
notebook_snapshot/templates/ribbon.css