Metadata-Version: 1.1
Name: notebook-snapshot
Version: 0.1.2
Summary: Execute a notebook, snapshot it as html (option: embedding all images) and store the result
Home-page: https://github.com/oscar6echo/notebook-snapshot
Author: oscar6echo
Author-email: olivier.borderies@gmail.com
License: MIT
Download-URL: https://github.com/oscar6echo/notebook-snapshot/tarball/0.1.2
Keywords: jupyter,nbconvert,embed images,execute
Platform: UNKNOWN
Classifier: Development Status :: 4 - Beta
Classifier: License :: OSI Approved :: MIT License
Classifier: Programming Language :: Python :: 3.5
Classifier: Programming Language :: Python :: 3.6
